{
  "id": 2,
  "titulo": "Empanadas",
  "imagen": [
    "/mocks/Imagenes/empanadas/empanadas.PNG",
    "/mocks/Imagenes/empanadas/empanadas1.jpg"


  ],
  "ingredientes": [
    "Masa para empanadas",
    "Carne picada",
    "Cebolla",
    "Huevo duro",
    "Aceitunas verdes",
    "Comino, pimentón dulce, sal y pimienta"
  ],
  "instrucciones": [
    "Preparar el relleno mezclando la carne picada con la cebolla picada, los huevos duros picados, las aceitunas picadas y los condimentos al gusto",
    "Rellenar las empanadas con la mezcla.",
    "Cerrar las empanadas y sellar los bordes.",
    "Hornear las empanadas en horno precalentado a 180°C hasta que estén doradas."
  ]
}